mlflow/__init__.py
mlflow/__main__.py
mlflow/_doctor.py
mlflow/_promptlab.py
mlflow/_spark_autologging.py
mlflow/cli.py
mlflow/client.py
mlflow/db.py
mlflow/environment_variables.py
mlflow/exceptions.py
mlflow/experiments.py
mlflow/ml_package_versions.py
mlflow/pypi_package_index.json
mlflow/runs.py
mlflow/version.py
mlflow/artifacts/__init__.py
mlflow/azure/__init__.py
mlflow/azure/client.py
mlflow/catboost/__init__.py
mlflow/data/__init__.py
mlflow/data/artifact_dataset_sources.py
mlflow/data/code_dataset_source.py
mlflow/data/dataset.py
mlflow/data/dataset_registry.py
mlflow/data/dataset_source.py
mlflow/data/dataset_source_registry.py
mlflow/data/delta_dataset_source.py
mlflow/data/digest_utils.py
mlflow/data/filesystem_dataset_source.py
mlflow/data/http_dataset_source.py
mlflow/data/huggingface_dataset.py
mlflow/data/huggingface_dataset_source.py
mlflow/data/numpy_dataset.py
mlflow/data/pandas_dataset.py
mlflow/data/pyfunc_dataset_mixin.py
mlflow/data/schema.py
mlflow/data/sources.py
mlflow/data/spark_dataset.py
mlflow/data/spark_dataset_source.py
mlflow/data/spark_delta_utils.py
mlflow/data/tensorflow_dataset.py
mlflow/deployments/__init__.py
mlflow/deployments/base.py
mlflow/deployments/cli.py
mlflow/deployments/constants.py
mlflow/deployments/interface.py
mlflow/deployments/plugin_manager.py
mlflow/deployments/utils.py
mlflow/deployments/databricks/__init__.py
mlflow/deployments/mlflow/__init__.py
mlflow/deployments/server/__init__.py
mlflow/deployments/server/app.py
mlflow/deployments/server/config.py
mlflow/deployments/server/constants.py
mlflow/deployments/server/runner.py
mlflow/diviner/__init__.py
mlflow/entities/__init__.py
mlflow/entities/_mlflow_object.py
mlflow/entities/dataset.py
mlflow/entities/dataset_input.py
mlflow/entities/dataset_summary.py
mlflow/entities/experiment.py
mlflow/entities/experiment_tag.py
mlflow/entities/file_info.py
mlflow/entities/input_tag.py
mlflow/entities/lifecycle_stage.py
mlflow/entities/metric.py
mlflow_by_ckl-2.81.0.dist-info/LICENSE.txt
mlflow_by_ckl-2.81.0.dist-info/METADATA
mlflow_by_ckl-2.81.0.dist-info/WHEEL
mlflow_by_ckl-2.81.0.dist-info/entry_points.txt
mlflow_by_ckl-2.81.0.dist-info/top_level.txt
mlflow_by_ckl-2.81.0.dist-info/RECORD
