Metadata-Version: 2.1
Name: mlflow-by-ckl
Version: 2.81.0
Summary: MLflow: A Platform for ML Development and Productionization
Home-page: https://mlflow.org/
Author: Databricks
License: Apache License 2.0
Project-URL: Bug Tracker, https://github.com/mlflow/mlflow/issues
Project-URL: Documentation, https://mlflow.org/docs/latest/index.html
Project-URL: Source Code, https://github.com/mlflow/mlflow
Keywords: ml ai databricks
Classifier: Intended Audience :: Developers
Classifier: Programming Language :: Python :: 3.8
Requires-Python: >=3.8
License-File: LICENSE.txt
Requires-Dist: click <9,>=7.0
Requires-Dist: cloudpickle <4
Requires-Dist: databricks-cli <1,>=0.8.7
Requires-Dist: entrypoints <1
Requires-Dist: gitpython <4,>=2.1.0
Requires-Dist: pyyaml <7,>=5.1
Requires-Dist: protobuf <5,>=3.12.0
Requires-Dist: pytz <2024
Requires-Dist: requests <3,>=2.17.3
Requires-Dist: packaging <24
Requires-Dist: importlib-metadata !=4.7.0,<8,>=3.7.0
Requires-Dist: sqlparse <1,>=0.4.0
Requires-Dist: alembic !=1.10.0,<2
Requires-Dist: docker <7,>=4.0.0
Requires-Dist: Flask <4
Requires-Dist: numpy <2
Requires-Dist: scipy <2
Requires-Dist: pandas <3
Requires-Dist: querystring-parser <2
Requires-Dist: sqlalchemy <3,>=1.4.0
Requires-Dist: scikit-learn <2
Requires-Dist: pyarrow <15,>=4.0.0
Requires-Dist: markdown <4,>=3.3
Requires-Dist: matplotlib <4
Requires-Dist: gunicorn <22 ; platform_system != "Windows"
Requires-Dist: Jinja2 <4,>=2.11 ; platform_system != "Windows"
Requires-Dist: waitress <3 ; platform_system == "Windows"
Requires-Dist: Jinja2 <4,>=3.0 ; platform_system == "Windows"
Provides-Extra: aliyun-oss
Requires-Dist: aliyunstoreplugin ; extra == 'aliyun-oss'
Provides-Extra: databricks
Requires-Dist: azure-storage-file-datalake >12 ; extra == 'databricks'
Requires-Dist: google-cloud-storage >=1.30.0 ; extra == 'databricks'
Requires-Dist: boto3 >1 ; extra == 'databricks'
Provides-Extra: extras
Requires-Dist: pyarrow ; extra == 'extras'
Requires-Dist: requests-auth-aws-sigv4 ; extra == 'extras'
Requires-Dist: boto3 ; extra == 'extras'
Requires-Dist: google-cloud-storage >=1.30.0 ; extra == 'extras'
Requires-Dist: azureml-core >=1.2.0 ; extra == 'extras'
Requires-Dist: pysftp ; extra == 'extras'
Requires-Dist: kubernetes ; extra == 'extras'
Requires-Dist: mlserver !=1.3.1,>=1.2.0 ; extra == 'extras'
Requires-Dist: mlserver-mlflow !=1.3.1,>=1.2.0 ; extra == 'extras'
Requires-Dist: virtualenv ; extra == 'extras'
Requires-Dist: prometheus-flask-exporter ; extra == 'extras'
Provides-Extra: gateway
Requires-Dist: pydantic <3,>=1.0 ; extra == 'gateway'
Requires-Dist: fastapi <1 ; extra == 'gateway'
Requires-Dist: uvicorn[standard] <1 ; extra == 'gateway'
Requires-Dist: watchfiles <1 ; extra == 'gateway'
Requires-Dist: aiohttp <4 ; extra == 'gateway'
Requires-Dist: boto3 <2,>=1.28.56 ; extra == 'gateway'
Provides-Extra: genai
Requires-Dist: pydantic <3,>=1.0 ; extra == 'genai'
Requires-Dist: fastapi <1 ; extra == 'genai'
Requires-Dist: uvicorn[standard] <1 ; extra == 'genai'
Requires-Dist: watchfiles <1 ; extra == 'genai'
Requires-Dist: aiohttp <4 ; extra == 'genai'
Requires-Dist: boto3 <2,>=1.28.56 ; extra == 'genai'
Provides-Extra: sqlserver
Requires-Dist: mlflow-dbstore ; extra == 'sqlserver'
Provides-Extra: xethub
Requires-Dist: mlflow-xethub ; extra == 'xethub'
